{
  "metrics": {
    "total_energy_J": 2.4619394707307,
    "avg_power_mW": 41.03232451217833,
    "peak_power_W": 0.3958186746057635,
    "total_footfalls": 1807,
    "floor_footfall_rate": 30.116666666666667,
    "avg_steps_per_person_min": 60.233333333333334,
    "mean_peak_power_mW": 100.87934765033421
  },
  "power_time_series": {
    "time_s": [
      0.0,
      0.04,
      0.08,
      0.12,
      0.16,
      0.2,
      0.24,
      0.28,
      0.32,
      0.36,
      0.4,
      0.44,
      0.48,
      0.52,
      0.56,
      0.6,
      0.64,
      0.68,
      0.72,
      0.76,
      0.8,
      0.84,
      0.88,
      0.92,
      0.96,
      1.0,
      1.04,
      1.08,
      1.12,
      1.16,
      1.2,
      1.24,
      1.28,
      1.32,
      1.36,
      1.4,
      1.44,
      1.48,
      1.52,
      1.56,
      1.6,
      1.64,
      1.68,
      1.72,
      1.76,
      1.8,
      1.84,
      1.88,
      1.92,
      1.96,
      2.0,
      2.04,
      2.08,
      2.12,
      2.16,
      2.2,
      2.24,
      2.28,
      2.32,
      2.36,
      2.4,
      2.44,
      2.48,
      2.52,
      2.56,
      2.6,
      2.64,
      2.68,
      2.72,
      2.76,
      2.8,
      2.84,
      2.88,
      2.92,
      2.96,
      3.0,
      3.04,
      3.08,
      3.12,
      3.16,
      3.2,
      3.24,
      3.28,
      3.32,
      3.36,
      3.4,
      3.44,
      3.48,
      3.52,
      3.56,
      3.6,
      3.64,
      3.68,
      3.72,
      3.76,
      3.8,
      3.84,
      3.88,
      3.92,
      3.96,
      4.0,
      4.04,
      4.08,
      4.12,
      4.16,
      4.2,
      4.24,
      4.28,
      4.32,
      4.36,
      4.4,
      4.44,
      4.48,
      4.52,
      4.56,
      4.6,
      4.64,
      4.68,
      4.72,
      4.76,
      4.8,
      4.84,
      4.88,
      4.92,
      4.96,
      5.0,
      5.04,
      5.08,
      5.12,
      5.16,
      5.2,
      5.24,
      5.28,
      5.32,
      5.36,
      5.4,
      5.44,
      5.48,
      5.52,
      5.56,
      5.6,
      5.64,
      5.68,
      5.72,
      5.76,
      5.8,
      5.84,
      5.88,
      5.92,
      5.96,
      6.0,
      6.04,
      6.08,
      6.12,
      6.16,
      6.2,
      6.24,
      6.28,
      6.32,
      6.36,
      6.4,
      6.44,
      6.48,
      6.52,
      6.56,
      6.6,
      6.64,
      6.68,
      6.72,
      6.76,
      6.8,
      6.84,
      6.88,
      6.92,
      6.96,
      7.0,
      7.04,
      7.08,
      7.12,
      7.16,
      7.2,
      7.24,
      7.28,
      7.32,
      7.36,
      7.4,
      7.44,
      7.48,
      7.52,
      7.56,
      7.6,
      7.64,
      7.68,
      7.72,
      7.76,
      7.8,
      7.84,
      7.88,
      7.92,
      7.96,
      8.0,
      8.04,
      8.08,
      8.12,
      8.16,
      8.2,
      8.24,
      8.28,
      8.32,
      8.36,
      8.4,
      8.44,
      8.48,
      8.52,
      8.56,
      8.6,
      8.64,
      8.68,
      8.72,
      8.76,
      8.8,
      8.84,
      8.88,
      8.92,
      8.96,
      9.0,
      9.04,
      9.08,
      9.12,
      9.16,
      9.2,
      9.24,
      9.28,
      9.32,
      9.36,
      9.4,
      9.44,
      9.48,
      9.52,
      9.56,
      9.6,
      9.64,
      9.68,
      9.72,
      9.76,
      9.8,
      9.84,
      9.88,
      9.92,
      9.96,
      10.0,
      10.04,
      10.08,
      10.12,
      10.16,
      10.2,
      10.24,
      10.28,
      10.32,
      10.36,
      10.4,
      10.44,
      10.48,
      10.52,
      10.56,
      10.6,
      10.64,
      10.68,
      10.72,
      10.76,
      10.8,
      10.84,
      10.88,
      10.92,
      10.96,
      11.0,
      11.04,
      11.08,
      11.12,
      11.16,
      11.2,
      11.24,
      11.28,
      11.32,
      11.36,
      11.4,
      11.44,
      11.48,
      11.52,
      11.56,
      11.6,
      11.64,
      11.68,
      11.72,
      11.76,
      11.8,
      11.84,
      11.88,
      11.92,
      11.96,
      12.0,
      12.04,
      12.08,
      12.12,
      12.16,
      12.2,
      12.24,
      12.28,
      12.32,
      12.36,
      12.4,
      12.44,
      12.48,
      12.52,
      12.56,
      12.6,
      12.64,
      12.68,
      12.72,
      12.76,
      12.8,
      12.84,
      12.88,
      12.92,
      12.96,
      13.0,
      13.04,
      13.08,
      13.12,
      13.16,
      13.2,
      13.24,
      13.28,
      13.32,
      13.36,
      13.4,
      13.44,
      13.48,
      13.52,
      13.56,
      13.6,
      13.64,
      13.68,
      13.72,
      13.76,
      13.8,
      13.84,
      13.88,
      13.92,
      13.96,
      14.0,
      14.04,
      14.08,
      14.12,
      14.16,
      14.2,
      14.24,
      14.28,
      14.32,
      14.36,
      14.4,
      14.44,
      14.48,
      14.52,
      14.56,
      14.6,
      14.64,
      14.68,
      14.72,
      14.76,
      14.8,
      14.84,
      14.88,
      14.92,
      14.96,
      15.0,
      15.04,
      15.08,
      15.12,
      15.16,
      15.2,
      15.24,
      15.28,
      15.32,
      15.36,
      15.4,
      15.44,
      15.48,
      15.52,
      15.56,
      15.6,
      15.64,
      15.68,
      15.72,
      15.76,
      15.8,
      15.84,
      15.88,
      15.92,
      15.96,
      16.0,
      16.04,
      16.08,
      16.12,
      16.16,
      16.2,
      16.24,
      16.28,
      16.32,
      16.36,
      16.4,
      16.44,
      16.48,
      16.52,
      16.56,
      16.6,
      16.64,
      16.68,
      16.72,
      16.76,
      16.8,
      16.84,
      16.88,
      16.92,
      16.96,
      17.0,
      17.04,
      17.08,
      17.12,
      17.16,
      17.2,
      17.24,
      17.28,
      17.32,
      17.36,
      17.4,
      17.44,
      17.48,
      17.52,
      17.56,
      17.6,
      17.64,
      17.68,
      17.72,
      17.76,
      17.8,
      17.84,
      17.88,
      17.92,
      17.96,
      18.0,
      18.04,
      18.08,
      18.12,
      18.16,
      18.2,
      18.24,
      18.28,
      18.32,
      18.36,
      18.4,
      18.44,
      18.48,
      18.52,
      18.56,
      18.6,
      18.64,
      18.68,
      18.72,
      18.76,
      18.8,
      18.84,
      18.88,
      18.92,
      18.96,
      19.0,
      19.04,
      19.08,
      19.12,
      19.16,
      19.2,
      19.24,
      19.28,
      19.32,
      19.36,
      19.4,
      19.44,
      19.48,
      19.52,
      19.56,
      19.6,
      19.64,
      19.68,
      19.72,
      19.76,
      19.8,
      19.84,
      19.88,
      19.92,
      19.96,
      20.0,
      20.04,
      20.08,
      20.12,
      20.16,
      20.2,
      20.24,
      20.28,
      20.32,
      20.36,
      20.4,
      20.44,
      20.48,
      20.52,
      20.56,
      20.6,
      20.64,
      20.68,
      20.72,
      20.76,
      20.8,
      20.84,
      20.88,
      20.92,
      20.96,
      21.0,
      21.04,
      21.08,
      21.12,
      21.16,
      21.2,
      21.24,
      21.28,
      21.32,
      21.36,
      21.4,
      21.44,
      21.48,
      21.52,
      21.56,
      21.6,
      21.64,
      21.68,
      21.72,
      21.76,
      21.8,
      21.84,
      21.88,
      21.92,
      21.96,
      22.0,
      22.04,
      22.08,
      22.12,
      22.16,
      22.2,
      22.24,
      22.28,
      22.32,
      22.36,
      22.4,
      22.44,
      22.48,
      22.52,
      22.56,
      22.6,
      22.64,
      22.68,
      22.72,
      22.76,
      22.8,
      22.84,
      22.88,
      22.92,
      22.96,
      23.0,
      23.04,
      23.08,
      23.12,
      23.16,
      23.2,
      23.24,
      23.28,
      23.32,
      23.36,
      23.4,
      23.44,
      23.48,
      23.52,
      23.56,
      23.6,
      23.64,
      23.68,
      23.72,
      23.76,
      23.8,
      23.84,
      23.88,
      23.92,
      23.96,
      24.0,
      24.04,
      24.08,
      24.12,
      24.16,
      24.2,
      24.24,
      24.28,
      24.32,
      24.36,
      24.4,
      24.44,
      24.48,
      24.52,
      24.56,
      24.6,
      24.64,
      24.68,
      24.72,
      24.76,
      24.8,
      24.84,
      24.88,
      24.92,
      24.96,
      25.0,
      25.04,
      25.08,
      25.12,
      25.16,
      25.2,
      25.24,
      25.28,
      25.32,
      25.36,
      25.4,
      25.44,
      25.48,
      25.52,
      25.56,
      25.6,
      25.64,
      25.68,
      25.72,
      25.76,
      25.8,
      25.84,
      25.88,
      25.92,
      25.96,
      26.0,
      26.04,
      26.08,
      26.12,
      26.16,
      26.2,
      26.24,
      26.28,
      26.32,
      26.36,
      26.4,
      26.44,
      26.48,
      26.52,
      26.56,
      26.6,
      26.64,
      26.68,
      26.72,
      26.76,
      26.8,
      26.84,
      26.88,
      26.92,
      26.96,
      27.0,
      27.04,
      27.08,
      27.12,
      27.16,
      27.2,
      27.24,
      27.28,
      27.32,
      27.36,
      27.4,
      27.44,
      27.48,
      27.52,
      27.56,
      27.6,
      27.64,
      27.68,
      27.72,
      27.76,
      27.8,
      27.84,
      27.88,
      27.92,
      27.96,
      28.0,
      28.04,
      28.08,
      28.12,
      28.16,
      28.2,
      28.24,
      28.28,
      28.32,
      28.36,
      28.4,
      28.44,
      28.48,
      28.52,
      28.56,
      28.6,
      28.64,
      28.68,
      28.72,
      28.76,
      28.8,
      28.84,
      28.88,
      28.92,
      28.96,
      29.0,
      29.04,
      29.08,
      29.12,
      29.16,
      29.2,
      29.24,
      29.28,
      29.32,
      29.36,
      29.4,
      29.44,
      29.48,
      29.52,
      29.56,
      29.6,
      29.64,
      29.68,
      29.72,
      29.76,
      29.8,
      29.84,
      29.88,
      29.92,
      29.96,
      30.0,
      30.04,
      30.08,
      30.12,
      30.16,
      30.2,
      30.24,
      30.28,
      30.32,
      30.36,
      30.4,
      30.44,
      30.48,
      30.52,
      30.56,
      30.6,
      30.64,
      30.68,
      30.72,
      30.76,
      30.8,
      30.84,
      30.88,
      30.92,
      30.96,
      31.0,
      31.04,
      31.08,
      31.12,
      31.16,
      31.2,
      31.24,
      31.28,
      31.32,
      31.36,
      31.4,
      31.44,
      31.48,
      31.52,
      31.56,
      31.6,
      31.64,
      31.68,
      31.72,
      31.76,
      31.8,
      31.84,
      31.88,
      31.92,
      31.96,
      32.0,
      32.04,
      32.08,
      32.12,
      32.16,
      32.2,
      32.24,
      32.28,
      32.32,
      32.36,
      32.4,
      32.44,
      32.48,
      32.52,
      32.56,
      32.6,
      32.64,
      32.68,
      32.72,
      32.76,
      32.8,
      32.84,
      32.88,
      32.92,
      32.96,
      33.0,
      33.04,
      33.08,
      33.12,
      33.16,
      33.2,
      33.24,
      33.28,
      33.32,
      33.36,
      33.4,
      33.44,
      33.48,
      33.52,
      33.56,
      33.6,
      33.64,
      33.68,
      33.72,
      33.76,
      33.8,
      33.84,
      33.88,
      33.92,
      33.96,
      34.0,
      34.04,
      34.08,
      34.12,
      34.16,
      34.2,
      34.24,
      34.28,
      34.32,
      34.36,
      34.4,
      34.44,
      34.48,
      34.52,
      34.56,
      34.6,
      34.64,
      34.68,
      34.72,
      34.76,
      34.8,
      34.84,
      34.88,
      34.92,
      34.96,
      35.0,
      35.04,
      35.08,
      35.12,
      35.16,
      35.2,
      35.24,
      35.28,
      35.32,
      35.36,
      35.4,
      35.44,
      35.48,
      35.52,
      35.56,
      35.6,
      35.64,
      35.68,
      35.72,
      35.76,
      35.8,
      35.84,
      35.88,
      35.92,
      35.96,
      36.0,
      36.04,
      36.08,
      36.12,
      36.16,
      36.2,
      36.24,
      36.28,
      36.32,
      36.36,
      36.4,
      36.44,
      36.48,
      36.52,
      36.56,
      36.6,
      36.64,
      36.68,
      36.72,
      36.76,
      36.8,
      36.84,
      36.88,
      36.92,
      36.96,
      37.0,
      37.04,
      37.08,
      37.12,
      37.16,
      37.2,
      37.24,
      37.28,
      37.32,
      37.36,
      37.4,
      37.44,
      37.48,
      37.52,
      37.56,
      37.6,
      37.64,
      37.68,
      37.72,
      37.76,
      37.8,
      37.84,
      37.88,
      37.92,
      37.96,
      38.0,
      38.04,
      38.08,
      38.12,
      38.16,
      38.2,
      38.24,
      38.28,
      38.32,
      38.36,
      38.4,
      38.44,
      38.48,
      38.52,
      38.56,
      38.6,
      38.64,
      38.68,
      38.72,
      38.76,
      38.8,
      38.84,
      38.88,
      38.92,
      38.96,
      39.0,
      39.04,
      39.08,
      39.12,
      39.16,
      39.2,
      39.24,
      39.28,
      39.32,
      39.36,
      39.4,
      39.44,
      39.48,
      39.52,
      39.56,
      39.6,
      39.64,
      39.68,
      39.72,
      39.76,
      39.8,
      39.84,
      39.88,
      39.92,
      39.96,
      40.0,
      40.04,
      40.08,
      40.12,
      40.16,
      40.2,
      40.24,
      40.28,
      40.32,
      40.36,
      40.4,
      40.44,
      40.48,
      40.52,
      40.56,
      40.6,
      40.64,
      40.68,
      40.72,
      40.76,
      40.8,
      40.84,
      40.88,
      40.92,
      40.96,
      41.0,
      41.04,
      41.08,
      41.12,
      41.16,
      41.2,
      41.24,
      41.28,
      41.32,
      41.36,
      41.4,
      41.44,
      41.48,
      41.52,
      41.56,
      41.6,
      41.64,
      41.68,
      41.72,
      41.76,
      41.8,
      41.84,
      41.88,
      41.92,
      41.96,
      42.0,
      42.04,
      42.08,
      42.12,
      42.16,
      42.2,
      42.24,
      42.28,
      42.32,
      42.36,
      42.4,
      42.44,
      42.48,
      42.52,
      42.56,
      42.6,
      42.64,
      42.68,
      42.72,
      42.76,
      42.8,
      42.84,
      42.88,
      42.92,
      42.96,
      43.0,
      43.04,
      43.08,
      43.12,
      43.16,
      43.2,
      43.24,
      43.28,
      43.32,
      43.36,
      43.4,
      43.44,
      43.48,
      43.52,
      43.56,
      43.6,
      43.64,
      43.68,
      43.72,
      43.76,
      43.8,
      43.84,
      43.88,
      43.92,
      43.96,
      44.0,
      44.04,
      44.08,
      44.12,
      44.16,
      44.2,
      44.24,
      44.28,
      44.32,
      44.36,
      44.4,
      44.44,
      44.48,
      44.52,
      44.56,
      44.6,
      44.64,
      44.68,
      44.72,
      44.76,
      44.8,
      44.84,
      44.88,
      44.92,
      44.96,
      45.0,
      45.04,
      45.08,
      45.12,
      45.16,
      45.2,
      45.24,
      45.28,
      45.32,
      45.36,
      45.4,
      45.44,
      45.48,
      45.52,
      45.56,
      45.6,
      45.64,
      45.68,
      45.72,
      45.76,
      45.8,
      45.84,
      45.88,
      45.92,
      45.96,
      46.0,
      46.04,
      46.08,
      46.12,
      46.16,
      46.2,
      46.24,
      46.28,
      46.32,
      46.36,
      46.4,
      46.44,
      46.48,
      46.52,
      46.56,
      46.6,
      46.64,
      46.68,
      46.72,
      46.76,
      46.8,
      46.84,
      46.88,
      46.92,
      46.96,
      47.0,
      47.04,
      47.08,
      47.12,
      47.16,
      47.2,
      47.24,
      47.28,
      47.32,
      47.36,
      47.4,
      47.44,
      47.48,
      47.52,
      47.56,
      47.6,
      47.64,
      47.68,
      47.72,
      47.76,
      47.8,
      47.84,
      47.88,
      47.92,
      47.96,
      48.0,
      48.04,
      48.08,
      48.12,
      48.16,
      48.2,
      48.24,
      48.28,
      48.32,
      48.36,
      48.4,
      48.44,
      48.48,
      48.52,
      48.56,
      48.6,
      48.64,
      48.68,
      48.72,
      48.76,
      48.8,
      48.84,
      48.88,
      48.92,
      48.96,
      49.0,
      49.04,
      49.08,
      49.12,
      49.16,
      49.2,
      49.24,
      49.28,
      49.32,
      49.36,
      49.4,
      49.44,
      49.48,
      49.52,
      49.56,
      49.6,
      49.64,
      49.68,
      49.72,
      49.76,
      49.8,
      49.84,
      49.88,
      49.92,
      49.96,
      50.0,
      50.04,
      50.08,
      50.12,
      50.16,
      50.2,
      50.24,
      50.28,
      50.32,
      50.36,
      50.4,
      50.44,
      50.48,
      50.52,
      50.56,
      50.6,
      50.64,
      50.68,
      50.72,
      50.76,
      50.8,
      50.84,
      50.88,
      50.92,
      50.96,
      51.0,
      51.04,
      51.08,
      51.12,
      51.16,
      51.2,
      51.24,
      51.28,
      51.32,
      51.36,
      51.4,
      51.44,
      51.48,
      51.52,
      51.56,
      51.6,
      51.64,
      51.68,
      51.72,
      51.76,
      51.8,
      51.84,
      51.88,
      51.92,
      51.96,
      52.0,
      52.04,
      52.08,
      52.12,
      52.16,
      52.2,
      52.24,
      52.28,
      52.32,
      52.36,
      52.4,
      52.44,
      52.48,
      52.52,
      52.56,
      52.6,
      52.64,
      52.68,
      52.72,
      52.76,
      52.8,
      52.84,
      52.88,
      52.92,
      52.96,
      53.0,
      53.04,
      53.08,
      53.12,
      53.16,
      53.2,
      53.24,
      53.28,
      53.32,
      53.36,
      53.4,
      53.44,
      53.48,
      53.52,
      53.56,
      53.6,
      53.64,
      53.68,
      53.72,
      53.76,
      53.8,
      53.84,
      53.88,
      53.92,
      53.96,
      54.0,
      54.04,
      54.08,
      54.12,
      54.16,
      54.2,
      54.24,
      54.28,
      54.32,
      54.36,
      54.4,
      54.44,
      54.48,
      54.52,
      54.56,
      54.6,
      54.64,
      54.68,
      54.72,
      54.76,
      54.8,
      54.84,
      54.88,
      54.92,
      54.96,
      55.0,
      55.04,
      55.08,
      55.12,
      55.16,
      55.2,
      55.24,
      55.28,
      55.32,
      55.36,
      55.4,
      55.44,
      55.48,
      55.52,
      55.56,
      55.6,
      55.64,
      55.68,
      55.72,
      55.76,
      55.8,
      55.84,
      55.88,
      55.92,
      55.96,
      56.0,
      56.04,
      56.08,
      56.12,
      56.16,
      56.2,
      56.24,
      56.28,
      56.32,
      56.36,
      56.4,
      56.44,
      56.48,
      56.52,
      56.56,
      56.6,
      56.64,
      56.68,
      56.72,
      56.76,
      56.8,
      56.84,
      56.88,
      56.92,
      56.96,
      57.0,
      57.04,
      57.08,
      57.12,
      57.16,
      57.2,
      57.24,
      57.28,
      57.32,
      57.36,
      57.4,
      57.44,
      57.48,
      57.52,
      57.56,
      57.6,
      57.64,
      57.68,
      57.72,
      57.76,
      57.8,
      57.84,
      57.88,
      57.92,
      57.96,
      58.0,
      58.04,
      58.08,
      58.12,
      58.16,
      58.2,
      58.24,
      58.28,
      58.32,
      58.36,
      58.4,
      58.44,
      58.48,
      58.52,
      58.56,
      58.6,
      58.64,
      58.68,
      58.72,
      58.76,
      58.8,
      58.84,
      58.88,
      58.92,
      58.96,
      59.0,
      59.04,
      59.08,
      59.12,
      59.16,
      59.2,
      59.24,
      59.28,
      59.32,
      59.36,
      59.4,
      59.44,
      59.48,
      59.52,
      59.56,
      59.6,
      59.64,
      59.68,
      59.72,
      59.76,
      59.8,
      59.84,
      59.88,
      59.92,
      59.96
    ],
    "power_mW": [
      0.0,
      -5.303546389556768e-05,
      -7.778469879315963e-05,
      0.03377957765238193,
      0.00724130946515994,
      0.011379376168907385,
      2.2834254977228685,
      2.3670673577274592,
      0.9495507518790802,
      0.25225456988442474,
      1.5229304404970057,
      0.20933598531058806,
      -0.018267095169388625,
      0.6267113598427687,
      -0.07111370130025857,
      3.6086486262263406,
      1.5791540495924128,
      5.883095904680502,
      4.435870108507212,
      3.910368039631962,
      1.0391216516580926,
      2.335600475664279,
      2.2395406712547583,
      2.840090778624127,
      10.404741136895268,
      0.14040883120464143,
      -0.7732286058583782,
      -0.09197255473480936,
      -0.28692342843328333,
      3.368583836898864,
      0.46855546902691003,
      1.8162817312941115,
      0.42637662028255363,
      -0.1772926729017854,
      7.228809979096695,
      1.5997550945172634,
      4.100198381024711,
      1.2174121372936497,
      1.4478216374413932,
      -0.24370189237288287,
      -0.43861332102324013,
      10.563188404148605,
      5.6176789180995,
      3.1501666125279826,
      4.48408382160892,
      2.3246502709071137,
      16.891898926555626,
      6.469591332518121,
      1.9720523629302988,
      12.332389496691576,
      3.843741666059941,
      1.3202396969518304,
      3.569417685980625,
      3.2689813490378583,
      0.31332266161143707,
      5.837427568167186,
      -0.5034798523411155,
      9.104202598791744,
      3.381181833219671,
      9.914206840207385,
      -0.3532492891622496,
      11.804822984231578,
      7.350180017994035,
      4.248648620887252,
      0.19553337051547715,
      9.978107593497043,
      2.289536712254403,
      -0.9378559883543858,
      5.183072720569726,
      4.341979397963769,
      11.348740443963834,
      0.8921266991350763,
      0.24474295523191358,
      26.528739352784214,
      4.466972699447069,
      1.386012515126822,
      0.28357402345591254,
      3.076963847661318,
      7.096844814981296,
      0.009142873409473395,
      16.292355624273114,
      4.845329312502145,
      10.141479869616887,
      3.039890419060498,
      6.7691996587200265,
      4.199866052658763,
      6.9653703951644275,
      3.6788104980587377,
      2.661566756614775,
      1.3995033024229997,
      12.023999419852771,
      10.593308468514806,
      21.68653322883074,
      1.6093071151885852,
      -1.9910431943799267,
      2.8503668858661513,
      4.973095444128717,
      11.773265170148761,
      2.699062867009161,
      3.1397540998341356,
      13.53036793557294,
      15.02651577737879,
      10.125983140625294,
      11.797806834778157,
      3.677287360005721,
      3.9988240348520776,
      0.8314181457080849,
      1.1749680205070945,
      27.57024774797401,
      13.096616133488226,
      19.095450068789432,
      3.935067407276449,
      -0.7521836985233676,
      1.203062153308565,
      -0.8341579253823284,
      0.903236518098538,
      13.492841232562114,
      10.608702601615505,
      26.902499664018364,
      8.63439856403403,
      2.5825201158227173,
      11.198840011843458,
      2.0376897078335787,
      27.269669257037776,
      16.340769281313783,
      11.658432829108278,
      -1.1943275046633062,
      2.504130800787152,
      3.0486286882478453,
      4.68238025177925,
      4.541996053831099,
      42.12895174896403,
      13.030984328736395,
      5.905444694917605,
      6.386183194081241,
      12.972660314062523,
      -0.43835218616550264,
      29.722955973284115,
      -1.393674116428656,
      4.0124336919689085,
      2.090991465095726,
      5.927110737957264,
      -1.7378554143760994,
      1.5207519545015202,
      10.834481166853038,
      10.76173561568794,
      4.038950551489506,
      -1.7448337415260085,
      5.642125168151324,
      4.804410932649716,
      2.6437904535967505,
      -0.0827179936209177,
      -0.07959007183444555,
      47.8757340702316,
      18.977587795859563,
      5.768647972473673,
      17.32266965643703,
      -0.5780055007562623,
      1.8463301036888424,
      2.585163245896638,
      0.6295848297526163,
      0.053149978338495885,
      17.10180121490623,
      0.9991065384156173,
      15.470565200757846,
      31.426524057678762,
      5.218222405140693,
      4.509711242690173,
      3.40490103042157,
      1.7632385605566014,
      11.647475491372461,
      9.581812957776492,
      -4.783269779522925,
      12.383749826426538,
      11.206717365553232,
      -3.1017460669460206,
      34.498690786762154,
      11.259098385011157,
      10.560179482983045,
      1.7263331097865375,
      20.49887990681043,
      4.252374500518741,
      18.741059103376756,
      10.418528332511556,
      15.912184387161687,
      -4.7016366684147215,
      7.1206236486887065,
      2.104940674257705,
      20.962237317604604,
      0.9688023093303855,
      -0.8008239657328886,
      1.1649421956789752,
      2.2942526354703396,
      7.37524857072458,
      0.0835916805499437,
      4.481968279378634,
      24.05718686873115,
      17.866583778641143,
      15.217787598658106,
      -0.7052224848393962,
      20.424624839648686,
      5.319166697518085,
      1.1455431366016455,
      3.8986195079360186,
      2.9465275192137597,
      -5.3007547640646635,
      31.300648057083436,
      18.07124749030109,
      9.868908719056435,
      26.686685235574714,
      2.8907891596929858,
      8.430920219780091,
      -2.4663023314417387,
      -3.881216589888936,
      27.55085772162147,
      15.98754243991607,
      9.416085852222977,
      -3.2694266047883502,
      9.074301865211964,
      20.946596498816916,
      22.110425297910297,
      7.282862801048395,
      3.6492306946627195,
      30.408850199592052,
      14.184706449327678,
      17.89811775427097,
      4.528477567760092,
      2.2110947812734594,
      36.98531779429004,
      0.6416044161881018,
      -0.5612836625914497,
      36.00112763456309,
      18.56631199837011,
      2.5507380225917586,
      -6.804332758520104,
      2.32823926643988,
      -4.649184348672009,
      26.632351760326856,
      0.8406235196503076,
      16.42716958590995,
      1.1011880131945873,
      -2.5730131098384845,
      23.71840559312588,
      33.907178363122625,
      17.200255146690324,
      -0.5429558338354568,
      7.522249213820942,
      2.658341628375638,
      -0.6911680139864984,
      0.44955519325640125,
      19.314387852901405,
      31.19434167899726,
      45.91923054420022,
      22.061533966933666,
      12.001981919468108,
      25.401390798947432,
      3.3664762734417764,
      7.225093421681095,
      -5.269814831180497,
      7.301341768851444,
      26.02710003478137,
      -11.089524798023831,
      3.489034763560994,
      2.8289197807964683,
      48.202953529511205,
      9.49620276342511,
      1.4127622271615792,
      3.475281488377391,
      -3.1465846917910767,
      9.071285495963366,
      5.4242946415001825,
      28.41344827265857,
      58.68103154045912,
      3.4685304466393063,
      4.607618982049644,
      17.354725153836625,
      -0.17101611706493713,
      -0.9081521175176022,
      26.600837908124397,
      5.572632049393178,
      55.49864062106735,
      18.651443206408658,
      40.48571082125818,
      21.492061092089898,
      25.558537481970234,
      18.182277879233766,
      22.446255220359035,
      31.69350967897344,
      13.776892291673448,
      -0.7824634382984641,
      -2.641819760697217,
      18.903836067948987,
      7.562596333343663,
      0.33899704509110506,
      1.6939238367967846,
      55.657651482533765,
      25.873215565184182,
      0.7660181547919365,
      31.112771508333026,
      -1.2890725429315353,
      15.915789047539874,
      38.200601771904985,
      17.270986913899833,
      4.72075076964984,
      13.037452387834492,
      50.03113867610409,
      -8.331134303944054,
      17.870240376737456,
      -3.2360856422428697,
      49.71217673107731,
      7.042064495855982,
      1.9832761725808723,
      15.565154134094428,
      28.903431665241897,
      8.086313629178221,
      31.069542552359053,
      40.24678157259132,
      9.982253262251106,
      30.60371868434686,
      1.3456625618459839,
      41.81876811890106,
      28.744275459075652,
      26.535747639229612,
      -16.007221490383472,
      38.28797915502946,
      5.0459657770147714,
      -2.776259754881494,
      -1.5249963694117241,
      49.87094899962585,
      21.598958569938986,
      -1.9489010019810848,
      3.103116553631935,
      14.907072814821731,
      4.068124092555081,
      20.434384193720234,
      29.83036531338712,
      21.26020407285978,
      -6.527170684743844,
      1.07476285188568,
      18.98565106228034,
      34.727573148259694,
      29.88582684361063,
      10.082287325161587,
      49.545393025510975,
      9.811173457109135,
      6.9078726967291,
      25.463690675344708,
      26.499983055828125,
      1.6848697670184265,
      33.91983927645015,
      -1.860865449089033,
      43.21886695504418,
      30.904163115877736,
      -10.037507894253395,
      31.47133764434784,
      1.2798780225296014,
      -4.901897416857537,
      20.283221808426788,
      23.55227859925435,
      2.275395207504971,
      34.01148363195716,
      11.428235933635733,
      -1.886777247634086,
      18.899999329619277,
      44.846043707707395,
      86.40599512651193,
      24.18082555846013,
      -8.306385421008144,
      -17.241742780640834,
      14.659003086094913,
      5.457990916738709,
      9.728069534503447,
      23.650132083048447,
      18.431548103471584,
      36.90354398395357,
      16.63490316457228,
      44.21933601179262,
      23.752873100136185,
      42.577456985497975,
      -2.2621959577691086,
      24.527247553351117,
      32.86210729186223,
      35.281805623583296,
      0.06424354819500877,
      77.08137684409166,
      -8.036823975089646,
      77.43307518731513,
      72.86218965532498,
      31.264277778291216,
      6.732952448885499,
      -17.12999929823411,
      21.893217690603706,
      0.7342450949749946,
      0.8961415592239064,
      11.204051028308015,
      -2.844000434613747,
      55.761800079757506,
      3.1474212592854656,
      8.473201858123502,
      -2.068378920739633,
      -0.5868654374125981,
      36.68810767521791,
      6.809848100203908,
      -4.029016040703937,
      7.285068155397312,
      98.7053222654879,
      23.248665550482883,
      94.32928700857701,
      100.3440270194389,
      12.607699826205021,
      22.8920209841732,
      43.3728644965754,
      14.392870395170565,
      22.575927963956133,
      3.093453795742107,
      14.625299605739883,
      1.677971468112105,
      23.113646604564053,
      45.929732852201255,
      19.12167746177218,
      2.708532270801811,
      17.482712294622615,
      64.13166793527125,
      -6.784696730960604,
      9.316356303315843,
      -2.0718520408991026,
      5.259638517600251,
      2.7708769860055327,
      46.36356021910615,
      6.7221973221194276,
      -3.0874121648452046,
      32.40787189042749,
      23.16575060010706,
      80.13636070012353,
      49.381903963649165,
      65.31823701106987,
      43.0018413377411,
      35.99544180400471,
      27.15445989954901,
      28.822360115213996,
      10.380802458342941,
      30.777581306210777,
      30.05732738995448,
      20.623720787625643,
      -2.2767282702371716,
      23.10987071496129,
      16.14971431513368,
      -1.829074283477894,
      61.758354953781236,
      -0.9279377572966041,
      0.8300985975893127,
      12.579794378893894,
      69.21371590260605,
      41.168442755775914,
      17.850079862085977,
      14.950721726336269,
      61.7373486741144,
      64.67732158728268,
      50.09917869475089,
      22.741103443934207,
      14.87890636889233,
      45.071346829899994,
      25.429298263190958,
      139.71011283763346,
      12.237298071340774,
      11.872809556734865,
      7.349026420570226,
      19.76235543236271,
      7.3229202562288265,
      32.715025737047654,
      2.743100956422495,
      34.20417168797485,
      11.01753509988157,
      -10.485601921310206,
      10.357322836128446,
      43.06265947319332,
      14.658721851617429,
      50.54377023492407,
      4.473787854607281,
      64.27593332487902,
      -2.389543313014997,
      20.540293925126463,
      35.03409982779715,
      -24.015124893666417,
      141.10810416154607,
      64.36935936790178,
      22.764162022667733,
      67.92530221628112,
      -4.69451309663782,
      72.07006412591,
      10.532808406651384,
      39.35795114830398,
      131.1216383816145,
      36.347182276415424,
      41.798408989734526,
      42.195360743335186,
      77.79603269342772,
      5.176785542289508,
      28.329536683941114,
      28.290967838614733,
      66.41252598569736,
      -6.379567230169414,
      17.940243039788584,
      1.961435826505209,
      5.1895570391131685,
      9.63669242639753,
      -3.7779302289351335,
      12.526960212632332,
      -8.680436907297917,
      4.6187661179502015,
      126.9865163767463,
      63.144951488993684,
      17.27799244065409,
      73.12906646745887,
      62.673237561341466,
      11.264636599676692,
      13.347213908446065,
      5.866494445676551,
      15.028596601666777,
      96.61945795017601,
      99.61366716732556,
      22.48345832080645,
      40.91304794616235,
      -20.58428786890687,
      1.1437147475987786,
      -1.2124212454267536,
      83.55877166392389,
      2.2450813242471668,
      8.412205865099054,
      25.77281582814628,
      48.12094765156871,
      6.877575639446576,
      0.19237932104942956,
      63.47702410675993,
      10.411799857081405,
      69.37826463502006,
      37.328146500613,
      66.8067977735518,
      73.87248161637672,
      80.76376137546504,
      16.104768120840163,
      13.49585142770593,
      -10.755972656852464,
      0.9612319468033093,
      13.187536173802528,
      92.96066448916918,
      -8.855812422456921,
      18.305890090914545,
      53.57790353997416,
      76.99821879435831,
      -6.418527606911084,
      45.40051862420569,
      101.8784450958492,
      33.33454016745918,
      63.85716686455112,
      70.08122220020141,
      35.70123453044971,
      62.44945441650884,
      13.235570670872221,
      -1.9969710493370485,
      9.998176975422268,
      8.54447332256214,
      66.17785874007431,
      71.90349685185993,
      110.81738842892719,
      82.0348816173464,
      -2.9702183633730783,
      11.565845944232933,
      -8.910209982175843,
      63.39972346512468,
      23.623606998057767,
      71.1174319028487,
      14.417392724340061,
      12.764845338779196,
      61.107643272578116,
      12.151255110723014,
      57.27416755524928,
      21.167186549064354,
      17.977735008116724,
      52.52679951543371,
      25.93340545809042,
      6.476100492591286,
      1.458295787699626,
      9.200252519349306,
      9.80281015881701,
      -17.055504929430754,
      38.275472215445916,
      139.10654137981737,
      132.78921625453677,
      3.9510076799729177,
      52.21060574672265,
      21.722973714759064,
      7.6564722715204425,
      18.393113947581696,
      5.657230766523469,
      -6.662641230832378,
      22.385720551767463,
      80.98547433628767,
      49.92825812934143,
      97.05619221647055,
      38.82258472282274,
      50.314085388009744,
      7.041542383305455,
      48.51462079431634,
      0.19184252770809707,
      25.28606601005645,
      8.824461823131458,
      -8.306550347146668,
      36.60779214055765,
      -19.819057321129208,
      70.31716790061182,
      13.389362018386919,
      17.3818559492247,
      86.07210748924388,
      14.350463027852811,
      14.745182362730702,
      47.69945633631778,
      39.11060879073602,
      4.650867797522551,
      7.7191882676288515,
      -17.256200877568517,
      106.24531463083997,
      12.798380087730266,
      25.706008590532292,
      14.980322773070043,
      58.126481784967154,
      63.38919227019346,
      -12.967351489578505,
      -3.7767978415104153,
      103.99525791717679,
      34.12560037753565,
      14.249473440969496,
      20.80573773434935,
      38.92411446810229,
      121.85978101206274,
      -0.8340782786717682,
      -6.395664938281698,
      40.44335051003145,
      59.03424990856365,
      9.590060300325831,
      36.653221358960764,
      4.688932143096736,
      -1.5569779310595777,
      13.069512326040922,
      23.954141109513216,
      -12.296356777142137,
      -15.292946029831,
      155.39978865454174,
      23.01285036480749,
      44.83773767185539,
      94.23637029792076,
      11.046465859180898,
      6.2884061384806955,
      1.7520607238878938,
      92.04162226070255,
      28.204997905966422,
      0.022780275770628577,
      60.73644441107717,
      -5.319188821204079,
      -10.596043181067216,
      112.3533090790545,
      79.86676487325894,
      3.9994048524931713,
      57.704362562503775,
      18.817524900384797,
      132.7651069431397,
      80.23571053995227,
      41.31357089931953,
      -1.483561693369495,
      43.43617524511956,
      79.2654621592419,
      150.53861627393417,
      5.840949997605094,
      43.12931451681834,
      -18.913066840994475,
      12.323693488951903,
      2.624794290625232,
      82.98062686702679,
      2.291576455007771,
      27.254232417988078,
      56.88933340672975,
      47.73713038586891,
      50.090522631016654,
      -1.2585368111643902,
      109.90183532217657,
      19.72294822257936,
      -2.5041747096565814,
      43.61798938847983,
      22.286241728124878,
      55.948448525327876,
      60.27538418538825,
      76.02520691284553,
      103.24964525102587,
      58.72876749617717,
      -1.6145028894243296,
      30.13674930707566,
      77.43137185011051,
      22.146763409395476,
      58.33786269977281,
      55.198955612468126,
      -8.182450467984381,
      -3.883894676022237,
      80.72626521425263,
      -10.621929462786284,
      69.62980622614623,
      66.74592330854168,
      19.482909714142238,
      -4.368653624694296,
      1.2567260627491805,
      58.73475971118225,
      48.95459967490012,
      11.306276705965956,
      49.17326982740633,
      80.51027406258982,
      0.9636477147410005,
      170.9662052053318,
      27.125332703235472,
      41.170784494397594,
      21.336437566105815,
      2.241423601162751,
      16.494717051728003,
      79.15947139031232,
      20.367019583318324,
      3.7476680885788483,
      16.517625174969908,
      165.5326735738072,
      99.81954294099538,
      8.355316147799385,
      151.04587848770734,
      80.60585716653179,
      -5.677805049003837,
      -1.0222384473195234,
      3.698546972316308,
      55.34389272214213,
      46.56820456125388,
      1.4385214921190936,
      133.3207892956807,
      -2.8040517990177705,
      13.159266372895218,
      27.636947437144954,
      3.6557436310431513,
      14.165457514536683,
      29.980998748669663,
      140.34158077060965,
      24.64471763249776,
      18.464931233012294,
      59.72024606512605,
      37.957788936864745,
      52.07842535912732,
      118.06440048860622,
      65.49928427041607,
      12.858531944871743,
      26.91394444684647,
      25.1518918996112,
      35.78924875753131,
      4.509177369016015,
      40.730705688901025,
      73.27647300417084,
      59.55005703375349,
      22.30474125303772,
      39.267977193048864,
      34.01250471824824,
      32.11366957793871,
      99.68834393504267,
      25.83300856167625,
      95.91189943057543,
      148.4886039634148,
      34.5087788544447,
      91.48107391826498,
      2.3071891664585564,
      -12.784849159402256,
      24.506317294054725,
      -7.035991085352578,
      25.84990631062567,
      33.1305515172744,
      -10.190265116975183,
      -10.585971717603115,
      -15.059854264123373,
      -13.936313366109232,
      49.83910842742034,
      21.035452585294934,
      14.108649295508258,
      177.02293251682022,
      83.51279234648246,
      1.088539642708497,
      78.82947765517656,
      49.47644055197742,
      107.64974671224081,
      39.40898536984605,
      105.03070059490938,
      41.03175011420035,
      19.364090552556945,
      -11.6066274666764,
      -22.479312234366944,
      9.998463275337599,
      -8.800866416177167,
      7.074002156912229,
      -4.6802019204506,
      9.419742746828774,
      23.795951762643597,
      -12.551613030339581,
      -11.387841988835135,
      -3.63450537230392,
      -4.854065667416307,
      107.39441504621539,
      118.73282080213698,
      64.30701590605281,
      122.61519234147755,
      60.43803105043821,
      85.41921770475369,
      66.10228913734773,
      37.90295927609577,
      62.04011263321263,
      111.14523357130679,
      48.819876989284694,
      18.37999592981987,
      -5.018082386271772,
      4.981056662472838,
      -5.369461492904293,
      21.88759959295794,
      13.277485216349305,
      -13.606122050077829,
      38.56471328072075,
      5.25856846707029,
      14.916900303092007,
      53.457323603822715,
      5.622268896587457,
      32.89830025642004,
      94.87329085676777,
      66.46442958762577,
      62.93825966994859,
      108.12957464850115,
      27.420481622129955,
      98.05233756719645,
      17.52377634147706,
      54.746511356967176,
      19.763117956017595,
      160.39119014467929,
      19.6268062895264,
      36.03574538846033,
      56.98780965266792,
      20.510140628857698,
      -25.367743666947717,
      83.3721776623122,
      -1.0866249879768475,
      4.082442197670844,
      -4.780680827479955,
      -25.413349841073796,
      10.356682036729126,
      194.45106373154886,
      29.27214880182305,
      15.29005741747369,
      10.66629172072453,
      60.08463240647188,
      80.20008578586157,
      31.745869017569817,
      66.17838159010603,
      -11.246568638085819,
      167.354893183429,
      250.22893819051006,
      -16.769395951769184,
      83.18093696925644,
      14.558366075561935,
      45.13493261038093,
      8.49290579294859,
      -6.648564803088952,
      10.732658153727925,
      79.5003610051026,
      11.6299343060291,
      -8.766203155346375,
      30.4140128839947,
      -4.674042061253658,
      32.92493616555703,
      94.07460103670928,
      22.532156231534373,
      9.348365944617854,
      9.73292284515992,
      48.64258816880351,
      1.1541188537194103,
      130.37989663820326,
      156.22771722675566,
      85.98660718832463,
      395.8186746057635,
      66.16447093625766,
      48.506347329208666,
      98.82580940035268,
      62.90135714675671,
      0.8106897912512068,
      -2.6035175330889615,
      7.1517051094360795,
      -2.5416017897441634,
      -0.34528942109091076,
      14.309212423768258,
      110.96549548733492,
      13.267604733641747,
      95.15903698587636,
      22.252390415701484,
      -25.498971418656424,
      176.84411524999177,
      126.46494088687632,
      114.24707661937106,
      71.8644265545123,
      120.27374884632991,
      87.1439501130169,
      57.55552067887493,
      122.653022231475,
      128.73800554348236,
      82.08554162936821,
      1.3805091259655455,
      50.986324340556166,
      162.85856658709008,
      71.21306477392864,
      98.15287198534861,
      22.69886809608579,
      9.508223236025515,
      60.107200511879455,
      31.9209105224445,
      -0.8423833070025921,
      -36.023394450467094,
      15.885635279119015,
      15.0723435283453,
      141.77078262764553,
      0.13001452435901228,
      78.96170298215566,
      17.20171241069579,
      24.42565424030363,
      37.16717598237551,
      13.145739904672382,
      50.82603234093597,
      82.46750399604252,
      0.6551663412892594,
      160.81190909312681,
      58.14183708820053,
      84.2380576293067,
      7.668027913126707,
      72.64856295407185,
      50.561497090701124,
      24.48930842031416,
      39.25117621179197,
      6.613221502334454,
      62.28499598455528,
      242.43124665957794,
      62.075317609469494,
      1.0671316621255755,
      10.734377258813765,
      15.610682188309966,
      7.409541512970463,
      90.56034068612462,
      40.74775633485217,
      70.37531127384256,
      73.42444186341623,
      -0.8657591182554825,
      238.6141935306938,
      65.90623125812556,
      -17.317094643203745,
      6.607485096992605,
      17.50860565999801,
      95.00565389771509,
      104.37614045130772,
      12.735941019798247,
      186.89261193401308,
      -23.778301565698712,
      71.81709744486398,
      94.6673366926234,
      106.79564921656493,
      122.28633332932759,
      4.941844450627286,
      26.08766176141275,
      44.91791922393418,
      46.43277724971995,
      80.95480351886408,
      102.6123836888928,
      5.038711431836873,
      -8.991305056895271,
      6.293345640393966,
      26.212843260680074,
      115.23810755443264,
      116.52831618908976,
      101.16010932201291,
      15.33497385435112,
      36.16573827389402,
      15.239839292917168,
      9.08594994939449,
      31.389500589057207,
      3.7984061704605665,
      3.574598044906452,
      50.454261177947046,
      144.3477093362162,
      48.540001373567065,
      66.19939527181629,
      68.75200208367005,
      0.9326674299359183,
      56.08744823030065,
      10.158117984758519,
      37.17067611592029,
      -2.970819985236517,
      96.55931037889331,
      64.31275928935065,
      119.31505925755914,
      40.58066833966478,
      96.92524267018143,
      24.007375420922017,
      20.86575686416836,
      79.5412032859133,
      86.26564580094964,
      -13.900085386126193,
      8.794517655530854,
      111.56838223416798,
      28.125733365754968,
      181.28539501356045,
      17.911367503328446,
      78.76670989207923,
      90.14213937564364,
      213.04094101313353,
      41.88252485914745,
      -27.173238703994684,
      46.75796260301013,
      110.23448031238559,
      118.33913132869611,
      53.94108632478378,
      214.8495293898236,
      63.60329701857381,
      24.31408529582768,
      65.54524075312429,
      55.89936272218665,
      -11.07071585633257,
      -18.761719959286438,
      47.027532152810636,
      140.48374813673937,
      56.388659065277125,
      0.6390536169931238,
      20.85036793220496,
      30.57383235574207,
      21.93516748145896,
      43.58667949207984,
      52.51787593780932,
      42.97968669561669,
      33.90054346755278,
      123.7273301036339,
      224.85187141774077,
      83.85153168705983,
      22.857460225168325,
      63.43112064530487,
      179.12645012540906,
      48.16723843063642,
      2.242083087615754,
      57.931574642907435,
      41.40007643127319,
      19.856082173987488,
      189.4613508171119,
      153.096336475528,
      103.7110192096975,
      32.94866875535263,
      20.87098456104286,
      -27.758062142414275,
      -6.708345868503329,
      22.75003879833548,
      5.288003918821005,
      105.18791586643772,
      26.244573130469462,
      -8.607787179528259,
      234.53990926100232,
      24.563507389117945,
      135.03951233292355,
      98.59405779630492,
      55.273540391112874,
      118.26789227961854,
      -20.200681152118705,
      -25.731067235028604,
      140.20800013616963,
      164.81209678516962,
      119.02890027135982,
      13.719884022918905,
      35.078414890190146,
      40.34283835608221,
      -26.9954470210223,
      193.18063736818658,
      136.95072456255275,
      16.856289384961087,
      -34.42885686865793,
      80.7072790573784,
      17.89759212394415,
      29.6005268670001,
      169.25604425597385,
      26.428799347058884,
      70.3976899789609,
      33.15219049375173,
      31.378235606098315,
      -4.428036968079141,
      15.247306030232721,
      75.49203240466795,
      -9.528263353786315,
      -13.712696655602485,
      117.77983417204041,
      122.629471189029,
      18.516859745901115,
      56.22066138903392,
      71.85867433054227,
      2.891634253955999,
      72.86764583572847,
      128.0372890139887,
      77.36375048331467,
      108.16487459112523,
      54.4807231233051,
      -5.767644490056512,
      144.15328906144254,
      165.214790958089,
      63.25027968068753,
      -21.429049982089055,
      -6.991679900750114,
      -27.211040299874867,
      38.52771737956573,
      135.3367081350143,
      -7.640982457161272,
      8.87914493377906,
      -18.018087863083565,
      78.0372068907127,
      73.48831122226329,
      -13.9401853662946,
      45.18120906618606,
      33.56099757945685,
      0.13405501923102747,
      97.30149743916172,
      56.24848596357879,
      9.306689049424222,
      76.27439177412043,
      74.96648651158466,
      80.73750005735292,
      -13.06141668555938,
      92.32015862494336,
      -21.06642669809844,
      151.51830342014705,
      183.43079571948806,
      95.40006914266996,
      196.5713437150498,
      37.81324739759384,
      88.96168004639549,
      10.651127974824703,
      -23.964793093909975,
      2.4767181079141665,
      22.021613881122448,
      63.159506707961555,
      128.18637992586446,
      45.30373009185951,
      103.68477385225106,
      21.48442174433285,
      55.47731506493392,
      66.55464205307737,
      102.06955945236018,
      -48.58827747489158,
      81.73978239770463,
      64.17047962600009,
      3.1957113737917098,
      99.34127022734174,
      132.7999694033224,
      30.310492847775095,
      82.56480871299487,
      18.8049669125121,
      -24.246106353075447,
      112.66556299656204,
      38.15861257908182,
      8.67953984675296,
      18.53620405336187,
      15.991811533638156,
      157.95473595767362,
      44.97269767958301,
      121.10520676981196,
      -18.901965461800785,
      273.90924403050576,
      -7.7321308898490315,
      8.026245788698816,
      -14.72358113805683,
      32.620996873362174,
      58.4181351322286,
      180.35463926185002,
      34.52131238191214,
      182.87185373355896,
      6.991988259073878,
      7.60916154234792,
      -13.689265796301697,
      19.920936569178593,
      111.21543834906333,
      84.25261607973766,
      -11.386401865820517,
      146.6633428908608,
      85.39954322850463,
      34.7924942325335,
      55.34028378065159,
      -22.43220444944427,
      50.240055918834514,
      13.428400315433464,
      116.8484813459969,
      143.83214108853792,
      20.993057618682087,
      27.6813140565082,
      136.74494387580438,
      87.56965767403813,
      85.7108776950497,
      105.24391256026,
      -2.544054227939796,
      117.48520720311717,
      52.69248092417911,
      40.812371697654726,
      136.7212857717277,
      23.111308852236334,
      -6.060530823333465,
      14.884218168987218,
      72.39628103712903,
      11.930898329950423,
      -12.800564888436838,
      26.41439656804323,
      16.410362297705205,
      111.57819276687064,
      17.89300038921482,
      180.25200172439781,
      53.84668329963205,
      94.08061337938989,
      145.74711015446695,
      185.9439872459987,
      194.22949312252058,
      76.05679808648347,
      14.345173590996296,
      80.06256927785671,
      167.31158387156597,
      33.81139344301687,
      -37.48378158570631,
      148.46791832150075,
      41.26860236840457,
      46.33202152672311,
      -5.729547145847391,
      10.993181876969516,
      -27.671384649266884,
      9.780658736872283,
      36.080755330658576,
      -10.058382467036608,
      59.84918543811091,
      79.8352041713315,
      22.043791596104256,
      38.46133277031072,
      56.800636370155644,
      61.97611889001564,
      54.69551752923962,
      20.059790803543365,
      106.59551643607301,
      146.0406006768551,
      194.37915495791458,
      101.34968702209335,
      171.3217572111887,
      324.9544811243368,
      66.64914662173516,
      66.64137144190363,
      20.524305539083798,
      65.48450274090101,
      59.97984755867947,
      5.750631239152426,
      26.754890976150136,
      67.03324160457669,
      7.3228495710964125,
      -10.292165691694777,
      11.150413040319052,
      -7.853554934968088,
      109.40272243878724,
      -13.171974873387171,
      85.98332979241263,
      -32.53846838197205,
      74.82113112772026,
      21.41306715839164,
      4.4810678834892315,
      56.312691481309685,
      187.2340167491302,
      41.398032943106955,
      20.51263789485347,
      57.631438193652684,
      17.82799030240767,
      122.87948821085592,
      104.92968470089181,
      -27.381878980747842,
      -28.47454695745455,
      79.23397464594473,
      32.238238314221235,
      195.08973170405852,
      54.666346504177454,
      175.85186116423301,
      24.029214817801403,
      5.277251609072664,
      96.65675052588085,
      -10.213268739306613,
      18.887663569088886,
      148.9348757014124,
      93.9636422338026,
      26.38865059063278,
      -14.77515538265095,
      -19.74925258514304,
      137.40436131283218,
      133.4370287637512,
      120.45921480910238,
      99.29547904334868,
      248.17773572385704,
      11.203558152942605,
      103.19936808275543,
      64.13250741566756,
      96.74558577347625,
      34.05032255517426,
      83.66014737976712,
      117.76050573941887,
      27.963843156797452,
      -31.308722837351866,
      43.169239323123776,
      69.40849532422533,
      110.93059340919353,
      -5.289592089184225,
      28.999839738617084,
      -0.6997656341241054,
      47.07957990180489,
      313.4314671699485,
      -10.031985445948521,
      23.766681183815308,
      101.66650593350823,
      367.3721445522915,
      166.50300124234008,
      162.88690087606028,
      27.302624111825935,
      34.210375352358824,
      130.5484730560238,
      108.89285262999238,
      95.94283765102318,
      102.45010474557148,
      188.00269402140657,
      -22.29570327395436,
      -4.2915255322846235,
      -33.368893676751554,
      14.108546283765122,
      48.866960846282836,
      5.378806038542905,
      146.16595518229758,
      53.58277722527305,
      194.03213169960054,
      90.54078638854435,
      172.3602594171325,
      90.35250638953585,
      26.80791819886963,
      6.777812284383344,
      393.42088899138616,
      39.17053110643565,
      -12.541271870389892,
      42.707183562015416,
      -9.128737768492101,
      105.75346945284991,
      169.7589058255744,
      78.01524759918266,
      12.820463689081407,
      1.191689745525082,
      -11.435604720006154,
      12.671935046199678,
      -20.663611245254287,
      74.47910369920407,
      -10.136119218572048,
      37.31532316183461,
      22.283263173360268,
      25.164369396762254,
      115.59430213253208,
      37.03597876009246,
      121.54803514452794,
      269.8391872933712,
      15.92836239620965,
      177.5006833995576,
      -10.999330111388872,
      197.4270047615505,
      121.06921959792771,
      304.04515761335915,
      94.61502354030671,
      53.17303677689722,
      -33.618374920138194,
      -11.60757581961036,
      -6.4921003759650375,
      -25.370328958956634,
      -20.734279643534137,
      0.355992138338479,
      20.712103028699858,
      197.35432498168848,
      -3.647898859981069,
      118.46992043297178,
      69.19946641403385,
      99.76953757268348,
      14.076552053253977,
      108.9991573662985,
      25.34514173984803,
      93.63461469428103,
      -3.1163437860186605,
      -36.363738130148704,
      119.12521564067902,
      129.81614477041603,
      126.31605159208448,
      210.05561909390735,
      283.64825467908616,
      49.74329968986524,
      -27.71812440545318,
      125.961867710771,
      -24.707636842833836,
      4.718363339179632,
      -36.06425148973358,
      2.0064968989572662,
      124.84971733346129,
      143.7432675297714,
      174.7672824080837,
      13.299561696499929,
      116.40811335416856,
      17.772893482117524,
      95.3160891274365,
      -4.906529134160564,
      -34.89036386542921,
      198.08210939260107,
      57.48927070919052,
      12.025253909669686,
      61.66690747534176,
      97.3452295355628,
      276.843205121736,
      53.213551088930444,
      86.39199974402345,
      195.8823543484982,
      48.73838002913544,
      56.32036753416969,
      49.07576208262299,
      -16.413336488199093,
      -18.605957204840706,
      15.47203667081476,
      239.7909884115279,
      183.84449300026517,
      111.11914721704785,
      34.65606850045333,
      -3.0405250126648298,
      5.130260396981612,
      110.45191504118179,
      17.993200765829442,
      -3.443555472049553,
      124.35712062665516,
      121.02512500966344,
      -27.72878028872583,
      7.163872664818882,
      80.19018139611944,
      269.7539726862601,
      288.38323881353034,
      52.18343744041931,
      9.616749584438367,
      16.62782410744512,
      13.15082983532534,
      94.35086877124377,
      135.0541364585638,
      -8.932005081859984,
      3.3978394993567917,
      154.4376721799381,
      74.53660623104952,
      33.9305392191136,
      -17.64282066828926,
      164.89908353470105,
      163.17238919748434,
      49.137690547993884,
      26.453689566945826,
      45.10901329854988,
      -11.483007929418143,
      204.43914268631414,
      151.52355572363518,
      33.953656718828995,
      47.33189419766859,
      10.113901421846094,
      117.79456882527484,
      5.383212575679863,
      22.831497369224962,
      15.9449277607564,
      -42.403797774568375,
      44.133357422424524,
      3.1415700648267375,
      23.37296946348033,
      24.45423271456093,
      339.4491426776085,
      73.44150409880967,
      -0.33030876300177425,
      72.03488882061038,
      74.69586814625018,
      114.11385671658536,
      8.25895296895851,
      40.32062506530565,
      36.044175824315516,
      112.49679576167182,
      32.63067632553884,
      122.3616292226648,
      85.34767677247146,
      24.578331929205888,
      83.94397546453547,
      -4.413236822415456,
      210.2533823574504,
      84.35398624988011,
      20.131449149062064,
      -1.128418830830924,
      -13.464647801811225,
      186.22679409372722,
      107.96127686757018,
      -10.803008854963991,
      35.303769035181176,
      34.318782572938744
    ]
  },
  "sessions": {
    "names": [
      "ina20uF_sess_001.npz",
      "ina20uF_sess_002.npz",
      "ina20uF_sess_003.npz",
      "ina20uF_sess_004.npz",
      "ina20uF_sess_005.npz",
      "ina20uF_sess_006.npz",
      "ina20uF_sess_007.npz",
      "ina20uF_sess_008.npz",
      "ina20uF_sess_009.npz",
      "ina20uF_sess_010.npz",
      "ina20uF_sess_011.npz",
      "ina20uF_sess_012.npz",
      "ina20uF_sess_013.npz",
      "ina20uF_sess_014.npz",
      "ina20uF_sess_015.npz",
      "ina20uF_sess_016.npz",
      "ina20uF_sess_017.npz",
      "ina20uF_sess_018.npz",
      "ina20uF_sess_019.npz",
      "ina20uF_sess_020.npz",
      "ina20uF_sess_021.npz",
      "ina20uF_sess_022.npz",
      "ina20uF_sess_023.npz",
      "ina20uF_sess_024.npz",
      "ina20uF_sess_025.npz",
      "ina20uF_sess_026.npz",
      "ina20uF_sess_027.npz",
      "ina20uF_sess_028.npz",
      "ina20uF_sess_029.npz",
      "ina20uF_sess_030.npz"
    ],
    "per_session_peak_mW": [
      7.7381706796586,
      6.3458224758504995,
      125.24574995040891,
      114.1043230891227,
      4.2633363045751995,
      7.3266644030809,
      124.3219301104545,
      143.9739763736724,
      5.8729634620249005,
      131.0127079486847,
      137.5274658203125,
      95.3955724835395,
      5.2834548987448,
      4.7774096019566,
      129.4323205947876,
      143.2175189256668,
      179.5256435871124,
      111.0612079501152,
      103.3238768577575,
      116.8117448687553,
      126.59037113189689,
      128.4516602754593,
      168.0169850587844,
      86.0764160752296,
      143.7841653823852,
      159.8623692989349,
      152.8006196022033,
      106.5293997526168,
      123.8061785697937,
      133.9004039764404
    ]
  },
  "cnn_step_detection": {
    "cnn_total_steps": 1705,
    "cnn_step_timeline_s": [
      0.12,
      0.12,
      0.12,
      0.12,
      0.12,
      0.12,
      0.28,
      0.28,
      0.28,
      0.44,
      0.44,
      0.44,
      0.6,
      0.6,
      0.6,
      0.6,
      0.6,
      0.6,
      0.6,
      0.76,
      0.76,
      0.76,
      0.76,
      0.76,
      0.76,
      0.76,
      0.76,
      0.76,
      0.76,
      0.92,
      0.92,
      0.92,
      0.92,
      1.08,
      1.08,
      1.08,
      1.24,
      1.24,
      1.24,
      1.4,
      1.4,
      1.56,
      1.56,
      1.56,
      1.56,
      1.56,
      1.56,
      1.56,
      1.72,
      1.72,
      1.72,
      1.72,
      1.72,
      1.72,
      1.72,
      1.72,
      1.72,
      1.88,
      1.88,
      1.88,
      1.88,
      2.04,
      2.04,
      2.04,
      2.04,
      2.2,
      2.2,
      2.2,
      2.2,
      2.36,
      2.36,
      2.36,
      2.36,
      2.52,
      2.52,
      2.52,
      2.52,
      2.68,
      2.68,
      2.68,
      2.68,
      2.84,
      2.84,
      2.84,
      2.84,
      2.84,
      2.84,
      3.0,
      3.0,
      3.0,
      3.0,
      3.16,
      3.16,
      3.16,
      3.16,
      3.16,
      3.16,
      3.16,
      3.16,
      3.32,
      3.32,
      3.32,
      3.32,
      3.48,
      3.64,
      3.64,
      3.64,
      3.8,
      3.8,
      3.8,
      3.8,
      3.8,
      3.8,
      3.96,
      3.96,
      3.96,
      3.96,
      3.96,
      3.96,
      3.96,
      4.12,
      4.12,
      4.28,
      4.28,
      4.28,
      4.28,
      4.28,
      4.28,
      4.28,
      4.28,
      4.44,
      4.6,
      4.6,
      4.6,
      4.6,
      4.6,
      4.6,
      4.76,
      4.76,
      4.76,
      4.76,
      4.92,
      4.92,
      4.92,
      4.92,
      4.92,
      4.92,
      5.08,
      5.08,
      5.08,
      5.08,
      5.24,
      5.24,
      5.24,
      5.24,
      5.24,
      5.24,
      5.4,
      5.4,
      5.4,
      5.56,
      5.56,
      5.56,
      5.72,
      5.72,
      5.72,
      5.72,
      5.72,
      5.88,
      5.88,
      5.88,
      5.88,
      6.04,
      6.04,
      6.04,
      6.04,
      6.04,
      6.04,
      6.04,
      6.04,
      6.2,
      6.2,
      6.2,
      6.2,
      6.36,
      6.36,
      6.52,
      6.52,
      6.52,
      6.52,
      6.68,
      6.68,
      6.68,
      6.68,
      6.84,
      6.84,
      6.84,
      6.84,
      7.0,
      7.0,
      7.0,
      7.0,
      7.0,
      7.0,
      7.0,
      7.16,
      7.16,
      7.16,
      7.32,
      7.32,
      7.32,
      7.32,
      7.32,
      7.48,
      7.48,
      7.64,
      7.64,
      7.64,
      7.8,
      7.8,
      7.8,
      7.8,
      7.8,
      7.8,
      7.96,
      7.96,
      8.12,
      8.12,
      8.12,
      8.12,
      8.12,
      8.12,
      8.28,
      8.28,
      8.28,
      8.28,
      8.28,
      8.44,
      8.44,
      8.44,
      8.6,
      8.6,
      8.6,
      8.6,
      8.76,
      8.76,
      8.76,
      8.76,
      8.92,
      8.92,
      8.92,
      8.92,
      8.92,
      8.92,
      8.92,
      9.08,
      9.08,
      9.08,
      9.24,
      9.24,
      9.24,
      9.24,
      9.24,
      9.4,
      9.56,
      9.56,
      9.56,
      9.56,
      9.56,
      9.56,
      9.56,
      9.72,
      9.72,
      9.72,
      9.72,
      9.72,
      9.88,
      9.88,
      10.04,
      10.04,
      10.04,
      10.04,
      10.04,
      10.04,
      10.04,
      10.2,
      10.2,
      10.2,
      10.36,
      10.36,
      10.36,
      10.36,
      10.52,
      10.52,
      10.52,
      10.52,
      10.52,
      10.68,
      10.68,
      10.68,
      10.84,
      10.84,
      10.84,
      10.84,
      11.0,
      11.0,
      11.0,
      11.0,
      11.0,
      11.16,
      11.16,
      11.16,
      11.16,
      11.16,
      11.16,
      11.16,
      11.32,
      11.32,
      11.32,
      11.32,
      11.48,
      11.48,
      11.48,
      11.48,
      11.64,
      11.64,
      11.8,
      11.8,
      11.8,
      11.8,
      11.8,
      11.96,
      11.96,
      11.96,
      11.96,
      11.96,
      11.96,
      11.96,
      11.96,
      12.12,
      12.12,
      12.12,
      12.28,
      12.28,
      12.28,
      12.28,
      12.44,
      12.44,
      12.44,
      12.44,
      12.44,
      12.6,
      12.6,
      12.6,
      12.76,
      12.76,
      12.76,
      12.76,
      12.76,
      12.76,
      12.92,
      12.92,
      12.92,
      12.92,
      13.08,
      13.08,
      13.08,
      13.08,
      13.08,
      13.08,
      13.08,
      13.08,
      13.24,
      13.24,
      13.24,
      13.24,
      13.4,
      13.4,
      13.56,
      13.56,
      13.56,
      13.56,
      13.56,
      13.72,
      13.72,
      13.72,
      13.72,
      13.72,
      13.72,
      13.72,
      13.88,
      13.88,
      13.88,
      13.88,
      13.88,
      14.04,
      14.04,
      14.04,
      14.04,
      14.04,
      14.2,
      14.2,
      14.2,
      14.2,
      14.36,
      14.36,
      14.36,
      14.36,
      14.52,
      14.52,
      14.52,
      14.52,
      14.52,
      14.68,
      14.68,
      14.68,
      14.68,
      14.84,
      14.84,
      14.84,
      14.84,
      14.84,
      14.84,
      14.84,
      15.0,
      15.0,
      15.16,
      15.16,
      15.16,
      15.16,
      15.16,
      15.32,
      15.32,
      15.32,
      15.32,
      15.32,
      15.32,
      15.32,
      15.48,
      15.48,
      15.48,
      15.48,
      15.64,
      15.64,
      15.8,
      15.8,
      15.8,
      15.8,
      15.96,
      15.96,
      15.96,
      16.12,
      16.12,
      16.12,
      16.12,
      16.12,
      16.28,
      16.28,
      16.28,
      16.28,
      16.28,
      16.28,
      16.28,
      16.28,
      16.28,
      16.28,
      16.44,
      16.44,
      16.44,
      16.6,
      16.6,
      16.6,
      16.6,
      16.76,
      16.76,
      16.76,
      16.76,
      16.76,
      16.92,
      16.92,
      16.92,
      17.08,
      17.08,
      17.24,
      17.24,
      17.24,
      17.24,
      17.4,
      17.4,
      17.4,
      17.4,
      17.4,
      17.4,
      17.4,
      17.4,
      17.56,
      17.56,
      17.56,
      17.56,
      17.72,
      17.72,
      17.72,
      17.72,
      17.72,
      17.72,
      17.88,
      17.88,
      18.04,
      18.04,
      18.04,
      18.04,
      18.2,
      18.2,
      18.2,
      18.2,
      18.36,
      18.36,
      18.36,
      18.36,
      18.36,
      18.36,
      18.36,
      18.52,
      18.52,
      18.52,
      18.52,
      18.52,
      18.52,
      18.68,
      18.68,
      18.68,
      18.84,
      18.84,
      18.84,
      18.84,
      19.0,
      19.0,
      19.0,
      19.0,
      19.16,
      19.16,
      19.16,
      19.32,
      19.32,
      19.32,
      19.32,
      19.32,
      19.32,
      19.32,
      19.32,
      19.48,
      19.48,
      19.48,
      19.48,
      19.48,
      19.64,
      19.64,
      19.64,
      19.64,
      19.8,
      19.8,
      19.8,
      19.8,
      19.8,
      19.96,
      19.96,
      19.96,
      19.96,
      19.96,
      19.96,
      20.12,
      20.12,
      20.12,
      20.28,
      20.28,
      20.28,
      20.28,
      20.28,
      20.44,
      20.44,
      20.44,
      20.44,
      20.44,
      20.44,
      20.44,
      20.44,
      20.6,
      20.76,
      20.76,
      20.76,
      20.76,
      20.76,
      20.76,
      20.76,
      20.92,
      20.92,
      20.92,
      21.08,
      21.08,
      21.08,
      21.08,
      21.08,
      21.24,
      21.24,
      21.24,
      21.24,
      21.4,
      21.4,
      21.4,
      21.4,
      21.4,
      21.4,
      21.4,
      21.4,
      21.56,
      21.56,
      21.56,
      21.56,
      21.56,
      21.56,
      21.72,
      21.88,
      21.88,
      21.88,
      22.04,
      22.04,
      22.04,
      22.04,
      22.04,
      22.2,
      22.2,
      22.2,
      22.2,
      22.2,
      22.2,
      22.36,
      22.36,
      22.52,
      22.52,
      22.52,
      22.52,
      22.52,
      22.52,
      22.52,
      22.52,
      22.52,
      22.68,
      22.68,
      22.68,
      22.68,
      22.84,
      22.84,
      22.84,
      22.84,
      23.0,
      23.0,
      23.0,
      23.0,
      23.0,
      23.16,
      23.16,
      23.16,
      23.16,
      23.32,
      23.32,
      23.32,
      23.32,
      23.32,
      23.48,
      23.48,
      23.48,
      23.48,
      23.48,
      23.64,
      23.64,
      23.64,
      23.64,
      23.64,
      23.8,
      23.8,
      23.8,
      23.8,
      23.96,
      23.96,
      23.96,
      23.96,
      23.96,
      24.12,
      24.12,
      24.12,
      24.28,
      24.28,
      24.28,
      24.28,
      24.44,
      24.44,
      24.44,
      24.44,
      24.6,
      24.6,
      24.6,
      24.6,
      24.6,
      24.6,
      24.6,
      24.6,
      24.76,
      24.76,
      24.76,
      24.76,
      24.76,
      24.92,
      24.92,
      24.92,
      24.92,
      24.92,
      24.92,
      25.08,
      25.08,
      25.24,
      25.24,
      25.24,
      25.24,
      25.24,
      25.4,
      25.4,
      25.4,
      25.56,
      25.56,
      25.56,
      25.56,
      25.56,
      25.72,
      25.72,
      25.88,
      25.88,
      25.88,
      25.88,
      25.88,
      25.88,
      26.04,
      26.04,
      26.04,
      26.04,
      26.2,
      26.2,
      26.2,
      26.36,
      26.36,
      26.36,
      26.36,
      26.36,
      26.52,
      26.52,
      26.52,
      26.52,
      26.52,
      26.52,
      26.68,
      26.68,
      26.68,
      26.68,
      26.68,
      26.84,
      26.84,
      26.84,
      26.84,
      26.84,
      27.0,
      27.0,
      27.0,
      27.16,
      27.16,
      27.16,
      27.16,
      27.32,
      27.32,
      27.32,
      27.32,
      27.32,
      27.48,
      27.48,
      27.48,
      27.48,
      27.48,
      27.48,
      27.48,
      27.48,
      27.64,
      27.64,
      27.64,
      27.64,
      27.8,
      27.8,
      27.8,
      27.8,
      27.8,
      27.96,
      27.96,
      27.96,
      28.12,
      28.12,
      28.12,
      28.28,
      28.28,
      28.28,
      28.28,
      28.28,
      28.44,
      28.44,
      28.44,
      28.44,
      28.44,
      28.44,
      28.44,
      28.6,
      28.6,
      28.6,
      28.6,
      28.6,
      28.76,
      28.76,
      28.76,
      28.92,
      28.92,
      28.92,
      28.92,
      28.92,
      29.08,
      29.08,
      29.08,
      29.08,
      29.08,
      29.24,
      29.24,
      29.24,
      29.24,
      29.24,
      29.4,
      29.4,
      29.4,
      29.4,
      29.56,
      29.56,
      29.56,
      29.72,
      29.72,
      29.72,
      29.72,
      29.72,
      29.72,
      29.88,
      29.88,
      29.88,
      29.88,
      29.88,
      29.88,
      29.88,
      30.04,
      30.2,
      30.2,
      30.2,
      30.2,
      30.2,
      30.36,
      30.36,
      30.36,
      30.36,
      30.36,
      30.36,
      30.52,
      30.52,
      30.52,
      30.52,
      30.52,
      30.52,
      30.52,
      30.68,
      30.84,
      30.84,
      30.84,
      30.84,
      30.84,
      31.0,
      31.0,
      31.16,
      31.16,
      31.16,
      31.16,
      31.16,
      31.16,
      31.32,
      31.32,
      31.32,
      31.32,
      31.32,
      31.48,
      31.48,
      31.48,
      31.48,
      31.48,
      31.48,
      31.48,
      31.48,
      31.48,
      31.64,
      31.64,
      31.96,
      31.96,
      31.96,
      31.96,
      31.96,
      32.12,
      32.12,
      32.12,
      32.12,
      32.28,
      32.28,
      32.28,
      32.28,
      32.28,
      32.28,
      32.28,
      32.28,
      32.44,
      32.44,
      32.44,
      32.44,
      32.44,
      32.44,
      32.6,
      32.6,
      32.6,
      32.76,
      32.76,
      32.76,
      32.92,
      33.08,
      33.08,
      33.08,
      33.08,
      33.08,
      33.08,
      33.24,
      33.24,
      33.24,
      33.24,
      33.24,
      33.24,
      33.24,
      33.24,
      33.4,
      33.4,
      33.4,
      33.4,
      33.4,
      33.4,
      33.56,
      33.56,
      33.56,
      33.72,
      33.72,
      33.88,
      33.88,
      33.88,
      33.88,
      33.88,
      34.04,
      34.04,
      34.04,
      34.2,
      34.2,
      34.2,
      34.2,
      34.2,
      34.2,
      34.36,
      34.36,
      34.36,
      34.36,
      34.36,
      34.36,
      34.36,
      34.36,
      34.68,
      34.68,
      34.68,
      34.84,
      34.84,
      34.84,
      34.84,
      35.0,
      35.0,
      35.0,
      35.16,
      35.16,
      35.16,
      35.16,
      35.16,
      35.16,
      35.16,
      35.16,
      35.16,
      35.32,
      35.32,
      35.32,
      35.32,
      35.32,
      35.48,
      35.48,
      35.48,
      35.48,
      35.48,
      35.64,
      35.8,
      35.8,
      35.8,
      35.96,
      35.96,
      35.96,
      35.96,
      35.96,
      35.96,
      35.96,
      36.12,
      36.12,
      36.12,
      36.12,
      36.12,
      36.28,
      36.28,
      36.28,
      36.28,
      36.28,
      36.44,
      36.44,
      36.44,
      36.44,
      36.6,
      36.6,
      36.6,
      36.6,
      36.76,
      36.76,
      36.76,
      36.92,
      36.92,
      36.92,
      36.92,
      37.08,
      37.08,
      37.08,
      37.08,
      37.08,
      37.08,
      37.24,
      37.24,
      37.24,
      37.24,
      37.4,
      37.4,
      37.4,
      37.4,
      37.4,
      37.56,
      37.56,
      37.56,
      37.56,
      37.56,
      37.56,
      37.72,
      37.88,
      37.88,
      37.88,
      37.88,
      37.88,
      37.88,
      38.04,
      38.04,
      38.04,
      38.04,
      38.04,
      38.04,
      38.2,
      38.2,
      38.2,
      38.36,
      38.36,
      38.36,
      38.36,
      38.36,
      38.36,
      38.52,
      38.52,
      38.52,
      38.52,
      38.52,
      38.52,
      38.68,
      38.68,
      38.68,
      38.68,
      38.84,
      39.0,
      39.0,
      39.0,
      39.0,
      39.0,
      39.16,
      39.16,
      39.16,
      39.16,
      39.32,
      39.32,
      39.32,
      39.48,
      39.48,
      39.48,
      39.48,
      39.48,
      39.48,
      39.48,
      39.64,
      39.64,
      39.64,
      39.8,
      39.8,
      39.8,
      39.8,
      39.8,
      39.8,
      39.96,
      39.96,
      39.96,
      39.96,
      39.96,
      40.12,
      40.12,
      40.12,
      40.12,
      40.28,
      40.28,
      40.28,
      40.28,
      40.28,
      40.44,
      40.44,
      40.44,
      40.44,
      40.6,
      40.6,
      40.6,
      40.6,
      40.6,
      40.6,
      40.76,
      40.76,
      40.76,
      40.76,
      40.76,
      40.76,
      40.92,
      40.92,
      40.92,
      40.92,
      41.08,
      41.08,
      41.08,
      41.08,
      41.08,
      41.24,
      41.24,
      41.24,
      41.24,
      41.4,
      41.4,
      41.4,
      41.4,
      41.4,
      41.4,
      41.56,
      41.56,
      41.56,
      41.56,
      41.56,
      41.72,
      41.72,
      41.72,
      41.88,
      41.88,
      41.88,
      41.88,
      41.88,
      42.04,
      42.04,
      42.04,
      42.04,
      42.2,
      42.2,
      42.36,
      42.36,
      42.36,
      42.36,
      42.52,
      42.52,
      42.52,
      42.52,
      42.52,
      42.52,
      42.68,
      42.68,
      42.68,
      42.68,
      42.68,
      42.84,
      42.84,
      42.84,
      42.84,
      42.84,
      43.0,
      43.0,
      43.0,
      43.0,
      43.16,
      43.16,
      43.16,
      43.32,
      43.32,
      43.32,
      43.32,
      43.32,
      43.32,
      43.32,
      43.48,
      43.48,
      43.48,
      43.64,
      43.64,
      43.64,
      43.64,
      43.64,
      43.8,
      43.8,
      43.96,
      43.96,
      43.96,
      43.96,
      43.96,
      43.96,
      43.96,
      43.96,
      43.96,
      44.12,
      44.12,
      44.12,
      44.12,
      44.12,
      44.12,
      44.12,
      44.28,
      44.28,
      44.28,
      44.44,
      44.44,
      44.44,
      44.6,
      44.6,
      44.6,
      44.6,
      44.6,
      44.76,
      44.76,
      44.76,
      44.92,
      44.92,
      44.92,
      44.92,
      44.92,
      44.92,
      44.92,
      45.08,
      45.08,
      45.08,
      45.08,
      45.08,
      45.24,
      45.24,
      45.24,
      45.24,
      45.24,
      45.24,
      45.24,
      45.4,
      45.56,
      45.56,
      45.56,
      45.56,
      45.72,
      45.72,
      45.72,
      45.72,
      45.88,
      45.88,
      45.88,
      45.88,
      45.88,
      45.88,
      46.04,
      46.04,
      46.04,
      46.04,
      46.04,
      46.04,
      46.2,
      46.2,
      46.2,
      46.36,
      46.36,
      46.36,
      46.52,
      46.52,
      46.52,
      46.52,
      46.52,
      46.52,
      46.68,
      46.68,
      46.68,
      46.68,
      46.68,
      46.84,
      46.84,
      46.84,
      46.84,
      46.84,
      46.84,
      46.84,
      47.0,
      47.0,
      47.0,
      47.0,
      47.0,
      47.16,
      47.16,
      47.32,
      47.32,
      47.48,
      47.48,
      47.48,
      47.48,
      47.64,
      47.64,
      47.64,
      47.64,
      47.64,
      47.64,
      47.64,
      47.8,
      47.8,
      47.8,
      47.8,
      47.8,
      47.8,
      47.8,
      47.96,
      47.96,
      48.12,
      48.12,
      48.12,
      48.28,
      48.28,
      48.28,
      48.44,
      48.44,
      48.44,
      48.6,
      48.6,
      48.6,
      48.6,
      48.6,
      48.6,
      48.76,
      48.76,
      48.76,
      48.76,
      48.76,
      48.76,
      48.76,
      48.76,
      48.92,
      48.92,
      48.92,
      48.92,
      48.92,
      48.92,
      49.08,
      49.08,
      49.08,
      49.24,
      49.24,
      49.4,
      49.4,
      49.56,
      49.56,
      49.56,
      49.72,
      49.72,
      49.72,
      49.72,
      49.72,
      49.72,
      49.72,
      49.72,
      49.72,
      49.72,
      49.88,
      49.88,
      49.88,
      49.88,
      49.88,
      49.88,
      50.04,
      50.04,
      50.04,
      50.2,
      50.2,
      50.2,
      50.36,
      50.36,
      50.52,
      50.52,
      50.52,
      50.52,
      50.52,
      50.52,
      50.52,
      50.68,
      50.68,
      50.68,
      50.68,
      50.68,
      50.84,
      50.84,
      50.84,
      50.84,
      51.0,
      51.0,
      51.0,
      51.0,
      51.0,
      51.0,
      51.16,
      51.16,
      51.16,
      51.16,
      51.32,
      51.32,
      51.32,
      51.48,
      51.48,
      51.48,
      51.48,
      51.48,
      51.64,
      51.64,
      51.64,
      51.64,
      51.64,
      51.64,
      51.64,
      51.8,
      51.8,
      51.8,
      51.8,
      51.8,
      51.8,
      51.96,
      51.96,
      51.96,
      51.96,
      51.96,
      52.12,
      52.12,
      52.12,
      52.28,
      52.28,
      52.28,
      52.28,
      52.44,
      52.44,
      52.44,
      52.44,
      52.44,
      52.44,
      52.6,
      52.6,
      52.6,
      52.6,
      52.6,
      52.6,
      52.76,
      52.76,
      52.76,
      52.76,
      52.76,
      52.92,
      52.92,
      52.92,
      52.92,
      52.92,
      53.08,
      53.08,
      53.24,
      53.24,
      53.24,
      53.4,
      53.4,
      53.4,
      53.4,
      53.4,
      53.4,
      53.56,
      53.56,
      53.56,
      53.56,
      53.56,
      53.56,
      53.56,
      53.72,
      53.72,
      53.72,
      53.88,
      53.88,
      53.88,
      53.88,
      53.88,
      54.04,
      54.04,
      54.04,
      54.04,
      54.04,
      54.04,
      54.2,
      54.2,
      54.2,
      54.2,
      54.2,
      54.36,
      54.36,
      54.36,
      54.52,
      54.52,
      54.52,
      54.52,
      54.68,
      54.68,
      54.68,
      54.68,
      54.68,
      54.68,
      54.68,
      54.68,
      54.84,
      54.84,
      54.84,
      54.84,
      54.84,
      55.0,
      55.0,
      55.16,
      55.16,
      55.16,
      55.16,
      55.16,
      55.16,
      55.16,
      55.32,
      55.32,
      55.32,
      55.32,
      55.48,
      55.48,
      55.48,
      55.48,
      55.64,
      55.64,
      55.64,
      55.64,
      55.64,
      55.64,
      55.64,
      55.8,
      55.8,
      55.8,
      55.8,
      55.8,
      55.96,
      55.96,
      56.12,
      56.12,
      56.12,
      56.12,
      56.12,
      56.28,
      56.28,
      56.44,
      56.44,
      56.44,
      56.44,
      56.6,
      56.6,
      56.6,
      56.6,
      56.6,
      56.6,
      56.6,
      56.76,
      56.76,
      56.76,
      56.76,
      56.76,
      56.92,
      56.92,
      56.92,
      56.92,
      57.08,
      57.08,
      57.08,
      57.08,
      57.08,
      57.24,
      57.24,
      57.4,
      57.4,
      57.4,
      57.4,
      57.4,
      57.4,
      57.4,
      57.56,
      57.56,
      57.56,
      57.56,
      57.56,
      57.56,
      57.56,
      57.72,
      57.72,
      57.88,
      57.88,
      57.88,
      57.88,
      57.88,
      58.04,
      58.04,
      58.04,
      58.04,
      58.2,
      58.2,
      58.2,
      58.36,
      58.36,
      58.36,
      58.36,
      58.36,
      58.52,
      58.52,
      58.52,
      58.52,
      58.52,
      58.52,
      58.52,
      58.52,
      58.68,
      58.84,
      58.84,
      58.84,
      58.84,
      59.0,
      59.0,
      59.0,
      59.0,
      59.16,
      59.16,
      59.16,
      59.16,
      59.32,
      59.32,
      59.32,
      59.32,
      59.32,
      59.32,
      59.48,
      59.48,
      59.48,
      59.48,
      59.48,
      59.48,
      59.48,
      59.64,
      59.64,
      59.8,
      59.8,
      59.8,
      59.8
    ]
  },
  "people_count_estimate": {
    "people_est_float": 8.211852073669434,
    "people_est_rounded": 8,
    "per_window_preds": [
      7.526355743408203,
      7.827151775360107,
      8.782092094421387,
      7.710227966308594,
      8.848522186279297,
      8.576763153076172
    ],
    "per_window_centers_s": [
      5.0,
      15.0,
      25.0,
      35.0,
      45.0,
      55.0
    ]
  }
}